consulsearch/__init__.py
consulsearch/application.py
consulsearch/client.py
consulsearch/search.py
consul_search-0.2.2.dist-info/METADATA
consul_search-0.2.2.dist-info/WHEEL
consul_search-0.2.2.dist-info/entry_points.txt
consul_search-0.2.2.dist-info/top_level.txt
consul_search-0.2.2.dist-info/RECORD
