Metadata-Version: 2.1
Name: consul-search
Version: 0.2.2
Summary: Search in the consul key/value
Home-page: UNKNOWN
Author: wuwentao
Author-email: wuwentao@patsnap.com
License: MIT
Keywords: consul,key_value,search
Platform: UNKNOWN
Classifier: Operating System :: OS Independent
Classifier: License :: OSI Approved :: MIT License
Classifier: Programming Language :: Python :: 3.5
Classifier: Programming Language :: Python :: 3.6
Classifier: Programming Language :: Python :: 3.7
Requires-Python: >=3.5
Requires-Dist: hsettings (>=0.1)
Requires-Dist: python-consul
Requires-Dist: colorama
Requires-Dist: diskcache
